LICENSE.md
MANIFEST.in
README.rst
setup.py
ovp_uploads/__init__.py
ovp_uploads/admin.py
ovp_uploads/apps.py
ovp_uploads/helpers.py
ovp_uploads/models.py
ovp_uploads/serializers.py
ovp_uploads/urls.py
ovp_uploads/views.py
ovp_uploads.egg-info/PKG-INFO
ovp_uploads.egg-info/SOURCES.txt
ovp_uploads.egg-info/dependency_links.txt
ovp_uploads.egg-info/not-zip-safe
ovp_uploads.egg-info/requires.txt
ovp_uploads.egg-info/top_level.txt
ovp_uploads/__pycache__/__init__.cpython-35.pyc
ovp_uploads/__pycache__/admin.cpython-35.pyc
ovp_uploads/__pycache__/apps.cpython-35.pyc
ovp_uploads/__pycache__/helpers.cpython-35.pyc
ovp_uploads/__pycache__/models.cpython-35.pyc
ovp_uploads/__pycache__/serializers.cpython-35.pyc
ovp_uploads/__pycache__/urls.cpython-35.pyc
ovp_uploads/__pycache__/views.cpython-35.pyc
ovp_uploads/locale/pt_BR/LC_MESSAGES/django.mo
ovp_uploads/locale/pt_BR/LC_MESSAGES/django.po
ovp_uploads/migrations/0001_initial.py
ovp_uploads/migrations/0002_uploadedimage.py
ovp_uploads/migrations/0003_uploadedimage_uuid.py
ovp_uploads/migrations/0004_add_category_and_name_to_images.py
ovp_uploads/migrations/0005_auto_20170522_2006.py
ovp_uploads/migrations/0006_auto_20170613_1424.py
ovp_uploads/migrations/__init__.py
ovp_uploads/migrations/__pycache__/0001_initial.cpython-35.pyc
ovp_uploads/migrations/__pycache__/0002_uploadedimage.cpython-35.pyc
ovp_uploads/migrations/__pycache__/0003_uploadedimage_uuid.cpython-35.pyc
ovp_uploads/migrations/__pycache__/0004_add_category_and_name_to_images.cpython-35.pyc
ovp_uploads/migrations/__pycache__/0005_auto_20170522_2006.cpython-35.pyc
ovp_uploads/migrations/__pycache__/0006_auto_20170613_1424.cpython-35.pyc
ovp_uploads/migrations/__pycache__/__init__.cpython-35.pyc
ovp_uploads/tests/__init__.py
ovp_uploads/tests/runtests.py
ovp_uploads/tests/test_execution.py
ovp_uploads/tests/test_models.py
ovp_uploads/tests/test_serializers.py
ovp_uploads/tests/test_views.py
ovp_uploads/tests/__pycache__/__init__.cpython-35.pyc
ovp_uploads/tests/__pycache__/test_execution.cpython-35.pyc
ovp_uploads/tests/__pycache__/test_models.cpython-35.pyc
ovp_uploads/tests/__pycache__/test_serializers.cpython-35.pyc
