Metadata-Version: 1.1
Name: ovp-uploads
Version: 1.0.4
Summary: This module has core upload functionality.
Home-page: https://github.com/OpenVolunteeringPlatform/django-ovp-uploads
Author: Atados
Author-email: arroyo@atados.com.br
License: AGPL
Download-URL: https://github.com/OpenVolunteeringPlatform/django-ovp-core/tarball/1.0.3
Platform: UNKNOWN
